{
  "steradian": {
    "scale": "1",
    "aliases": [
      "steradians",
      "sr"
    ]
  },
  "quectosteradian": {
    "scale": "1E-30",
    "aliases": [
      "quectosteradians",
      "qsr"
    ]
  },
  "rontosteradian": {
    "scale": "1E-27",
    "aliases": [
      "rontosteradians",
      "rsr"
    ]
  },
  "yoctosteradian": {
    "scale": "1E-24",
    "aliases": [
      "yoctosteradians",
      "ysr"
    ]
  },
  "zeptosteradian": {
    "scale": "1E-21",
    "aliases": [
      "zeptosteradians",
      "zsr"
    ]
  },
  "attosteradian": {
    "scale": "1E-18",
    "aliases": [
      "attosteradians",
      "asr"
    ]
  },
  "femtosteradian": {
    "scale": "1E-15",
    "aliases": [
      "femtosteradians",
      "fsr"
    ]
  },
  "picosteradian": {
    "scale": "1E-12",
    "aliases": [
      "picosteradians",
      "psr"
    ]
  },
  "nanosteradian": {
    "scale": "1E-9",
    "aliases": [
      "nanosteradians",
      "nsr"
    ]
  },
  "microsteradian": {
    "scale": "1E-6",
    "aliases": [
      "microsteradians",
      "\u00b5sr"
    ]
  },
  "millisteradian": {
    "scale": "1E-3",
    "aliases": [
      "millisteradians",
      "msr"
    ]
  },
  "centisteradian": {
    "scale": "1E-2",
    "aliases": [
      "centisteradians",
      "csr"
    ]
  },
  "decisteradian": {
    "scale": "1E-1",
    "aliases": [
      "decisteradians",
      "dsr"
    ]
  },
  "decasteradian": {
    "scale": "1E+1",
    "aliases": [
      "decasteradians",
      "dasr"
    ]
  },
  "hectosteradian": {
    "scale": "1E+2",
    "aliases": [
      "hectosteradians",
      "hsr"
    ]
  },
  "kilosteradian": {
    "scale": "1E+3",
    "aliases": [
      "kilosteradians",
      "ksr"
    ]
  },
  "megasteradian": {
    "scale": "1E+6",
    "aliases": [
      "megasteradians",
      "Msr"
    ]
  },
  "gigasteradian": {
    "scale": "1E+9",
    "aliases": [
      "gigasteradians",
      "Gsr"
    ]
  },
  "terasteradian": {
    "scale": "1E+12",
    "aliases": [
      "terasteradians",
      "Tsr"
    ]
  },
  "petasteradian": {
    "scale": "1E+15",
    "aliases": [
      "petasteradians",
      "Psr"
    ]
  },
  "exasteradian": {
    "scale": "1E+18",
    "aliases": [
      "exasteradians",
      "Esr"
    ]
  },
  "zettasteradian": {
    "scale": "1E+21",
    "aliases": [
      "zettasteradians",
      "Zsr"
    ]
  },
  "yottasteradian": {
    "scale": "1E+24",
    "aliases": [
      "yottasteradians",
      "Ysr"
    ]
  },
  "ronnasteradian": {
    "scale": "1E+27",
    "aliases": [
      "ronnasteradians",
      "Rsr"
    ]
  },
  "quettasteradian": {
    "scale": "1E+30",
    "aliases": [
      "quettasteradians",
      "Qsr"
    ]
  }
}